{
    "os": "Linux-5.15.0-105-generic-x86_64-with-glibc2.31",
    "python": "3.10.4",
    "heartbeatAt": "2024-05-11T21:43:41.971870",
    "startedAt": "2024-05-11T21:43:41.065475",
    "docker": null,
    "gpu": "NVIDIA GeForce GTX 1080 Ti",
    "gpu_count": 4,
    "cpu_count": 12,
    "cuda": null,
    "args": [],
    "state": "running",
    "program": "/home/ravi/raviProject/CODE/model/transformersMain.py",
    "codePath": "model/transformersMain.py",
    "git": {
        "remote": "https://github.com/kamalravi/TelegramThreatLevel.git",
        "commit": "31533657c20b0c6ee69a80f05c3f2a925b9180da"
    },
    "email": "rkk.bme@gmail.com",
    "root": "/home/ravi/raviProject/CODE",
    "host": "Lamdba2",
    "username": "ravi",
    "executable": "/home/ravi/miniconda3/envs/transformers/bin/python"
}
